uw_restclients_space-1.2.6.dist-info/licenses/LICENSE
uw_space/VERSION
uw_space/__init__.py
uw_space/dao.py
uw_space/models.py
uw_space/test.py
uw_space/utils.py
uw_space/resources/space/file/space/v2/facility.json_facility_code_MDR
uw_space/resources/space/file/space/v2/facility.json_facility_code_MEB
uw_space/resources/space/file/space/v2/facility.json_long_name_Allen_Library
uw_space/resources/space/file/space/v2/facility.json_long_name_None
uw_space/resources/space/file/space/v2/facility.json_street_668_NE_Northlake_Way
uw_space/resources/space/file/space/v2/facility/1072.json
uw_space/resources/space/file/space/v2/facility/1107.json
uw_space/resources/space/file/space/v2/facility/1347.json
uw_space/resources/space/file/space/v2/facility/6471.json
uw_space/tests/__init__.py
uw_space/tests/test_dao.py
uw_space/tests/test_facilities.py
uw_restclients_space-1.2.6.dist-info/METADATA
uw_restclients_space-1.2.6.dist-info/WHEEL
uw_restclients_space-1.2.6.dist-info/top_level.txt
uw_restclients_space-1.2.6.dist-info/RECORD
